[{"items":[{"id":"m1","name":"Mac & Cheese","price":"8.99","description":"Creamy cheddar cheese mixed with perfectly cooked macaroni, topped with crispy breadcrumbs. A classic comfort food.","image":"images/mac-and-cheese.jpg","quantity":1},{"id":"m2","name":"Margherita Pizza","price":"12.99","description":"A classic pizza with fresh mozzarella, tomatoes, and basil on a thin and crispy crust.","image":"images/margherita-pizza.jpg","quantity":1},{"id":"m3","name":"Caesar Salad","price":"7.99","description":"Romaine lettuce tossed in Caesar dressing, topped with croutons and parmesan shavings.","image":"images/caesar-salad.jpg","quantity":1},{"id":"m7","name":"Steak Frites","price":"17.99","description":"Succulent steak cooked to your preference, served with crispy golden fries and herb butter.","image":"images/steak-frites.jpg","quantity":1},{"id":"m8","name":"Sushi Roll Platter","price":"15.99","description":"An assortment of fresh sushi rolls including California, Spicy Tuna, and Eel Avocado.","image":"images/sushi-roll-platter.jpg","quantity":1}],"customer":{"name":"d","email":"dd@dd","street":"fdfdsf","postal-code":"2e23","city":"3232"},"id":"50.84820565092674"},{"customer":{"name":"d","email":"dd@dd","street":"fdfdsf","postal-code":"2e23","city":"3232"},"items":[{"id":"m1","name":"Mac & Cheese","price":"8.99","description":"Creamy cheddar cheese mixed with perfectly cooked macaroni, topped with crispy breadcrumbs. A classic comfort food.","image":"images/mac-and-cheese.jpg","quantity":1},{"id":"m2","name":"Margherita Pizza","price":"12.99","description":"A classic pizza with fresh mozzarella, tomatoes, and basil on a thin and crispy crust.","image":"images/margherita-pizza.jpg","quantity":1},{"id":"m3","name":"Caesar Salad","price":"7.99","description":"Romaine lettuce tossed in Caesar dressing, topped with croutons and parmesan shavings.","image":"images/caesar-salad.jpg","quantity":1},{"id":"m7","name":"Steak Frites","price":"17.99","description":"Succulent steak cooked to your preference, served with crispy golden fries and herb butter.","image":"images/steak-frites.jpg","quantity":1},{"id":"m8","name":"Sushi Roll Platter","price":"15.99","description":"An assortment of fresh sushi rolls including California, Spicy Tuna, and Eel Avocado.","image":"images/sushi-roll-platter.jpg","quantity":1}],"id":"804.1859689474946"},{"customer":{"name":"Vanna York","email":"gumovij@mailinator.com","street":"Labore nisi ea culpa","postal-code":"Provident aut amet","city":"Mollitia veritatis n"},"items":[{"id":"m3","name":"Caesar Salad","price":"7.99","description":"Romaine lettuce tossed in Caesar dressing, topped with croutons and parmesan shavings.","image":"images/caesar-salad.jpg","quantity":1},{"id":"m2","name":"Margherita Pizza","price":"12.99","description":"A classic pizza with fresh mozzarella, tomatoes, and basil on a thin and crispy crust.","image":"images/margherita-pizza.jpg","quantity":1}],"id":"76.281388338024"},{"customer":{"name":"Vanna York","email":"gumovij@mailinator.com","street":"Labore nisi ea culpa","postal-code":"Provident aut amet","city":"Mollitia veritatis n"},"items":[{"id":"m3","name":"Caesar Salad","price":"7.99","description":"Romaine lettuce tossed in Caesar dressing, topped with croutons and parmesan shavings.","image":"images/caesar-salad.jpg","quantity":1},{"id":"m2","name":"Margherita Pizza","price":"12.99","description":"A classic pizza with fresh mozzarella, tomatoes, and basil on a thin and crispy crust.","image":"images/margherita-pizza.jpg","quantity":1}],"id":"12.325798422801792"},{"customer":{"name":"Vanna York","email":"gumovij@mailinator.com","street":"Labore nisi ea culpa","postal-code":"Provident aut amet","city":"Mollitia veritatis n"},"items":[{"id":"m3","name":"Caesar Salad","price":"7.99","description":"Romaine lettuce tossed in Caesar dressing, topped with croutons and parmesan shavings.","image":"images/caesar-salad.jpg","quantity":1},{"id":"m2","name":"Margherita Pizza","price":"12.99","description":"A classic pizza with fresh mozzarella, tomatoes, and basil on a thin and crispy crust.","image":"images/margherita-pizza.jpg","quantity":1}],"id":"557.5032970380438"},{"customer":{"name":"Vanna York","email":"gumovij@mailinator.com","street":"Labore nisi ea culpa","postal-code":"Provident aut amet","city":"Mollitia veritatis n"},"items":[{"id":"m3","name":"Caesar Salad","price":"7.99","description":"Romaine lettuce tossed in Caesar dressing, topped with croutons and parmesan shavings.","image":"images/caesar-salad.jpg","quantity":1},{"id":"m2","name":"Margherita Pizza","price":"12.99","description":"A classic pizza with fresh mozzarella, tomatoes, and basil on a thin and crispy crust.","image":"images/margherita-pizza.jpg","quantity":1}],"id":"812.9098850874639"},{"customer":{"name":"Vanna York","email":"gumovij@mailinator.com","street":"Labore nisi ea culpa","postal-code":"Provident aut amet","city":"Mollitia veritatis n"},"items":[{"id":"m3","name":"Caesar Salad","price":"7.99","description":"Romaine lettuce tossed in Caesar dressing, topped with croutons and parmesan shavings.","image":"images/caesar-salad.jpg","quantity":1},{"id":"m2","name":"Margherita Pizza","price":"12.99","description":"A classic pizza with fresh mozzarella, tomatoes, and basil on a thin and crispy crust.","image":"images/margherita-pizza.jpg","quantity":1}],"id":"54.00697302158797"},{"customer":{"name":"Cheryl Webster","email":"gyfa@mailinator.com","street":"Maxime fuga Ut omni","postal-code":"Consequatur Maxime ","city":"Est vel eos sint exc"},"items":[{"id":"m2","name":"Margherita Pizza","price":"12.99","description":"A classic pizza with fresh mozzarella, tomatoes, and basil on a thin and crispy crust.","image":"images/margherita-pizza.jpg","quantity":1},{"id":"m3","name":"Caesar Salad","price":"7.99","description":"Romaine lettuce tossed in Caesar dressing, topped with croutons and parmesan shavings.","image":"images/caesar-salad.jpg","quantity":1}],"id":"347.8470466895227"},{"customer":{"name":"Baker Tyson","email":"vypononyty@mailinator.com","street":"Excepteur esse nost","postal-code":"Amet a quia id et i","city":"Asperiores laborum q"},"items":[{"id":"m2","name":"Margherita Pizza","price":"12.99","description":"A classic pizza with fresh mozzarella, tomatoes, and basil on a thin and crispy crust.","image":"images/margherita-pizza.jpg","quantity":1},{"id":"m3","name":"Caesar Salad","price":"7.99","description":"Romaine lettuce tossed in Caesar dressing, topped with croutons and parmesan shavings.","image":"images/caesar-salad.jpg","quantity":1}],"id":"675.8633823386342"},{"customer":{"name":"Clare Wood","email":"tufykyd@mailinator.com","street":"Rerum amet fugiat q","postal-code":"Laboriosam necessit","city":"Ut officia exercitat"},"items":[{"id":"m2","name":"Margherita Pizza","price":"12.99","description":"A classic pizza with fresh mozzarella, tomatoes, and basil on a thin and crispy crust.","image":"images/margherita-pizza.jpg","quantity":1},{"id":"m3","name":"Caesar Salad","price":"7.99","description":"Romaine lettuce tossed in Caesar dressing, topped with croutons and parmesan shavings.","image":"images/caesar-salad.jpg","quantity":1}],"id":"862.5790070952952"}]